elatentlpips/__init__.py
elatentlpips/ada_aug.py
elatentlpips/custom_ops.py
elatentlpips/elatentlpips.py
elatentlpips/style_misc.py
elatentlpips/vgg16.py
elatentlpips/style_ops/__init__.py
elatentlpips/style_ops/bias_act.cpp
elatentlpips/style_ops/bias_act.cu
elatentlpips/style_ops/bias_act.h
elatentlpips/style_ops/bias_act.py
elatentlpips/style_ops/conv2d_gradfix.py
elatentlpips/style_ops/conv2d_resample.py
elatentlpips/style_ops/filtered_lrelu.cpp
elatentlpips/style_ops/filtered_lrelu.cu
elatentlpips/style_ops/filtered_lrelu.h
elatentlpips/style_ops/filtered_lrelu.py
elatentlpips/style_ops/filtered_lrelu_ns.cu
elatentlpips/style_ops/filtered_lrelu_rd.cu
elatentlpips/style_ops/filtered_lrelu_wr.cu
elatentlpips/style_ops/fma.py
elatentlpips/style_ops/grid_sample_gradfix.py
elatentlpips/style_ops/upfirdn2d.cpp
elatentlpips/style_ops/upfirdn2d.cu
elatentlpips/style_ops/upfirdn2d.h
elatentlpips/style_ops/upfirdn2d.py
elatentlpips/style_ops/dnnlib/__init__.py
elatentlpips/style_ops/dnnlib/util.py
elatentlpips-0.2.dist-info/LICENSE
elatentlpips-0.2.dist-info/LICENSE-NVIDIA
elatentlpips-0.2.dist-info/METADATA
elatentlpips-0.2.dist-info/WHEEL
elatentlpips-0.2.dist-info/top_level.txt
elatentlpips-0.2.dist-info/RECORD
